lokryn_compliance_log/__init__.py
lokryn_compliance_log/mappings.py
lokryn_compliance_log/v1/__init__.py
lokryn_compliance_log/v1/logentry_pb2.py
lokryn_compliance_log-0.2.0.dist-info/METADATA
lokryn_compliance_log-0.2.0.dist-info/WHEEL
lokryn_compliance_log-0.2.0.dist-info/licenses/LICENSE
lokryn_compliance_log-0.2.0.dist-info/RECORD
