Metadata-Version: 2.4
Name: lokryn-compliance-log
Version: 0.2.0
Summary: Protocol Buffers schema for compliance-grade audit logging. Built for SOC2, HIPAA, and PCI environments.
Project-URL: Homepage, https://github.com/lokryn-llc/compliance-log-schema
Project-URL: Documentation, https://github.com/lokryn-llc/compliance-log-schema#readme
Project-URL: Repository, https://github.com/lokryn-llc/compliance-log-schema.git
Project-URL: Issues, https://github.com/lokryn-llc/compliance-log-schema/issues
Author-email: Lokryn <hello@lokryn.com>
License-Expression: Apache-2.0
License-File: LICENSE
Keywords: agents,ai,audit,compliance,hipaa,logging,pci,protobuf,soc2
Classifier: Development Status :: 4 - Beta
Classifier: Intended Audience :: Developers
Classifier: License :: OSI Approved :: Apache Software License
Classifier: Operating System :: OS Independent
Classifier: Programming Language :: Python :: 3
Classifier: Programming Language :: Python :: 3.9
Classifier: Programming Language :: Python :: 3.10
Classifier: Programming Language :: Python :: 3.11
Classifier: Programming Language :: Python :: 3.12
Classifier: Programming Language :: Python :: 3.13
Classifier: Topic :: Security
Classifier: Topic :: System :: Logging
Requires-Python: >=3.9
Requires-Dist: protobuf>=4.0
